upload_testing/__init__.py
upload_testing/example.py
upload_testing/untitled4.py
upload_testing-0.0.1.dist-info/METADATA
upload_testing-0.0.1.dist-info/WHEEL
upload_testing-0.0.1.dist-info/licenses/LICENSE.txt
upload_testing-0.0.1.dist-info/RECORD
